sc3020/__init__.py
sc3020/interface.py
sc3020/project.py
sc3020/whatif.py
sc3020/assets/__init__.py
sc3020/assets/images/NTU_Logo.png
sc3020/assets/images/__init__.py
sc3020/database/ExecutionTree.py
sc3020/database/__init__.py
sc3020/database/setup.sql
sc3020/database/tcph.py
sc3020/database/visualizer.py
sc3020/examples/__init__.py
sc3020/examples/example1.sql
sc3020/examples/example2.sql
sc3020/examples/example3.sql
sc3020/examples/example4.sql
sc3020/examples/example5.sql
sc3020/static/__init__.py
sc3020/static/css/__init__.py
sc3020/static/css/bootstrap.css
sc3020/static/css/custom.css
sc3020/static/js/__init__.py
sc3020/static/js/bootstrap.bundle.js
sc3020/templates/__init__.py
sc3020/templates/connection_guide.md
sc3020/templates/header.html
sc3020/templates/index.html
sc3020/templates/layout.html
sc3020/templates/title.html
sc3020_g6_2024-0.2.0.dist-info/METADATA
sc3020_g6_2024-0.2.0.dist-info/WHEEL
sc3020_g6_2024-0.2.0.dist-info/entry_points.txt
sc3020_g6_2024-0.2.0.dist-info/top_level.txt
sc3020_g6_2024-0.2.0.dist-info/RECORD
