Metadata-Version: 2.1
Name: sc3020-g6-2024
Version: 0.2.0
Summary: SC3020 Project-2
Author-email: Pu Fanyi <FPU001@e.ntu.edu.sg>, Zhang Kaichen <ZHAN0564@e.ntu.edu.sg>, Cui Nan <C220133@e.ntu.edu.sg>, Shan Yi <SH0005YI@e.ntu.edu.sg>, Tian Yidong <YTIAN006@e.ntu.edu.sg>
License: MIT
Project-URL: Homepage, https://pufanyi.github.io/SC4002-Project/
Project-URL: Repository, https://github.com/pufanyi/SC4002-Project
Classifier: Programming Language :: Python :: 3
Classifier: License :: OSI Approved :: MIT License
Classifier: Operating System :: OS Independent
Requires-Python: >=3.9
Requires-Dist: fastapi
Requires-Dist: uvicorn
Requires-Dist: jinja2
Requires-Dist: gradio>=4.44.1
Requires-Dist: datasets
Requires-Dist: psycopg[binary]>=3.1.8
Requires-Dist: plotly
Requires-Dist: kaleido
Requires-Dist: igraph
Provides-Extra: opt
